jayditya_rl_update/__init__.py
jayditya_rl_update/qlearning.py
jayditya_rl_update-0.0.1.dist-info/licenses/LICENSE
jayditya_rl_update-0.0.1.dist-info/METADATA
jayditya_rl_update-0.0.1.dist-info/WHEEL
jayditya_rl_update-0.0.1.dist-info/top_level.txt
jayditya_rl_update-0.0.1.dist-info/RECORD
