Metadata-Version: 2.4
Name: jayditya-rl-update
Version: 0.0.1
Summary: Q-learning update helper function (Reinforcement Learning)
Author-email: Jayditya Pratap Singh <example@example.com>
License: MIT
Project-URL: Homepage, https://pypi.org/project/jayditya-rl-update/
Keywords: reinforcement-learning,q-learning,rl
Classifier: Programming Language :: Python :: 3
Classifier: License :: OSI Approved :: MIT License
Classifier: Topic :: Scientific/Engineering :: Artificial Intelligence
Requires-Python: >=3.8
License-File: LICENSE
Dynamic: license-file
